CVAT_Dataset_Converter/__init__.py
CVAT_Dataset_Converter/app.py
CVAT_Dataset_Converter/cli.py
CVAT_Dataset_Converter/config.py
CVAT_Dataset_Converter/cvat_parser.py
CVAT_Dataset_Converter/jobs.py
CVAT_Dataset_Converter/lifespan.py
CVAT_Dataset_Converter/tickets.py
CVAT_Dataset_Converter/frontend/index.html
CVAT_Dataset_Converter/frontend/css/styles.css
CVAT_Dataset_Converter/frontend/js/api.js
CVAT_Dataset_Converter/frontend/js/app.js
CVAT_Dataset_Converter/frontend/js/config.js
CVAT_Dataset_Converter/frontend/js/dom.js
CVAT_Dataset_Converter/frontend/js/session.js
cvat_dataset_converter-0.1.0.dist-info/METADATA
cvat_dataset_converter-0.1.0.dist-info/WHEEL
cvat_dataset_converter-0.1.0.dist-info/entry_points.txt
cvat_dataset_converter-0.1.0.dist-info/top_level.txt
cvat_dataset_converter-0.1.0.dist-info/RECORD
