Metadata-Version: 2.4
Name: cvat-dataset-converter
Version: 0.1.0
Summary: CVAT Dataset Converter Utility (FastAPI backend + static frontend)
Author-email: Yahiya Mulla <yahiya6006@gmail.com>
License: MIT
Requires-Python: >=3.9
Requires-Dist: fastapi>=0.122.0
Requires-Dist: uvicorn[standard]>=0.38.0
Requires-Dist: pillow>=11.2.1
Requires-Dist: python-multipart>=0.0.20
